karl_jiang_demo/__init__.py
karl_jiang_demo-0.1.0.dist-info/WHEEL
karl_jiang_demo-0.1.0.dist-info/entry_points.txt
karl_jiang_demo-0.1.0.dist-info/METADATA
karl_jiang_demo-0.1.0.dist-info/RECORD
